strynova_dj_hotreload/__init__.py
strynova_dj_hotreload/apps.py
strynova_dj_hotreload/hot_reload.py
strynova_dj_hotreload/watcher.py
strynova_dj_hotreload/websocket.py
strynova_dj_hotreload/__pycache__/__init__.cpython-312.pyc
strynova_dj_hotreload/__pycache__/apps.cpython-312.pyc
strynova_dj_hotreload/__pycache__/hot_reload.cpython-312.pyc
strynova_dj_hotreload/__pycache__/watcher.cpython-312.pyc
strynova_dj_hotreload/__pycache__/websocket.cpython-312.pyc
strynova_dj_hotreload/static/strynova_dj_hotreload/js/hot-reload.js
strynova_dj_hotreload/templatetags/__init__.py
strynova_dj_hotreload/templatetags/strynova_hot_reload.py
strynova_dj_hotreload/templatetags/__pycache__/__init__.cpython-312.pyc
strynova_dj_hotreload/templatetags/__pycache__/strynova_hot_reload.cpython-312.pyc
strynova_dj_hotreload-0.4.dist-info/licenses/LICENSE
tests/__init__.py
tests/manage.py
tests/test_project/__init__.py
tests/test_project/settings.py
tests/test_project/urls.py
tests/test_project/wsgi.py
strynova_dj_hotreload-0.4.dist-info/METADATA
strynova_dj_hotreload-0.4.dist-info/WHEEL
strynova_dj_hotreload-0.4.dist-info/top_level.txt
strynova_dj_hotreload-0.4.dist-info/RECORD
